dbt_to_cypher/__init__.py
dbt_to_cypher/cli.py
dbt_to_cypher/cypher.py
dbt_to_cypher/dbt_to_cypher.py
dbt_to_cypher/extractor.py
dbt_to_cypher/graph.py
dbt_to_cypher-0.1.1.dist-info/METADATA
dbt_to_cypher-0.1.1.dist-info/WHEEL
dbt_to_cypher-0.1.1.dist-info/entry_points.txt
dbt_to_cypher-0.1.1.dist-info/licenses/LICENSE
dbt_to_cypher-0.1.1.dist-info/RECORD
