Metadata-Version: 2.4
Name: dbt-to-cypher
Version: 0.1.1
Summary: Extract dependency graphs from dbt (including model and column dependencies) and convert them to Cypher queries
Project-URL: Homepage, https://github.com/laphoang/dbt-to-cypher
Project-URL: Repository, https://github.com/laphoang/dbt-to-cypher
Project-URL: Issues, https://github.com/laphoang/dbt-to-cypher/issues
Author-email: Lap Hoang <hoangduclap102@gmail.com>
License: MIT License
License-File: LICENSE
Keywords: cypher,dbt,dependencies,graph,lineage,neo4j
Classifier: Development Status :: 3 - Alpha
Classifier: Intended Audience :: Developers
Classifier: License :: OSI Approved :: MIT License
Classifier: Programming Language :: Python :: 3
Classifier: Programming Language :: Python :: 3.9
Classifier: Programming Language :: Python :: 3.10
Classifier: Programming Language :: Python :: 3.11
Classifier: Programming Language :: Python :: 3.12
Classifier: Topic :: Database
Classifier: Topic :: Software Development :: Libraries :: Python Modules
Requires-Python: >=3.9
Requires-Dist: dbt-artifacts-parser>=0.8.2
Requires-Dist: dbt-colibri>=0.2.7
Requires-Dist: networkx>=3.0
Requires-Dist: pyyaml>=6.0
Provides-Extra: dev
Requires-Dist: dbt-artifacts-parser>=0.8.2; extra == 'dev'
Requires-Dist: mypy>=1.0; extra == 'dev'
Requires-Dist: pre-commit>=3.0; extra == 'dev'
Requires-Dist: pytest-cov>=4.0; extra == 'dev'
Requires-Dist: pytest>=7.0; extra == 'dev'
Requires-Dist: python-dotenv>=1.0.0; extra == 'dev'
Requires-Dist: ruff>=0.1.0; extra == 'dev'
Requires-Dist: types-pyyaml>=6.0; extra == 'dev'
